.gitignore
Dockerfile
Makefile
README.md
poetry.lock
pyproject.toml
setup.py
.github/workflows/docker-image.yml
data/.gitignore
modelchallangekleiner/__init__.py
modelchallangekleiner.egg-info/PKG-INFO
modelchallangekleiner.egg-info/SOURCES.txt
modelchallangekleiner.egg-info/dependency_links.txt
modelchallangekleiner.egg-info/top_level.txt
modelchallangekleiner/data/__init__.py
modelchallangekleiner/data/fetch_data.py
modelchallangekleiner/features/__init__.py
modelchallangekleiner/features/transformer.py
modelchallangekleiner/features/transformers/__init__.py
modelchallangekleiner/features/transformers/custom_transformers.py
modelchallangekleiner/model/__init__.py
modelchallangekleiner/model/train.py
modelchallangekleiner/utils/__init__.py
modelchallangekleiner/utils/utils.py
models/.gitignore
tests/data/test_fetch_data.py
tests/features/test_custom_transformers.py
tests/model/test_train.py
tests/model/test_dataset/uci_dataset.xls