Metadata-Version: 2.1
Name: modelchallangekleiner
Version: 0.1.0
Summary: model challange
Home-page: UNKNOWN
Author: kleiner matias
License: UNKNOWN
Platform: UNKNOWN
Requires-Python: >=3.8
